{"recordSetCount":9,"metaData":{"price":"1"},"resourceId":"https://aas129.watsoncommerce.ibm.com/search/resources/store/1/productview/byCategory/13","breadCrumbTrailEntryViewExtended":[{"0":{"label":"Hardware","type_":"FACET_ENTRY_CATEGORY","value":"11"},"1":{"label":"Lighting","type_":"FACET_ENTRY_CATEGORY","value":"13"}}],"breadCrumbTrailEntryView":[{"label":"Hardware","type_":"FACET_ENTRY_CATEGORY","value":"11"},{"label":"Lighting","type_":"FACET_ENTRY_CATEGORY","value":"13"}],"catalogEntryView":[{"hasSingleSKU":false,"resourceId":"https://aas129.watsoncommerce.ibm.com/search/resources/store/1/productview/byId/13842","uniqueID":"13842","partNumber":"LA042_4201","shortDescription":"Energy-efficient, screw-in spiral bulb","catalogEntryTypeCode":"ProductBean","thumbnail":"https://my4.digitalexperience.ibm.com/30817b50-78a2-4463-b5e2-2d7c39231327/dxdam/ExtendedSitesCatalogAssetStore/images/catalog/hardware/lighting/fla42_lighting/200x310/la042_4201.jpg","buyable":"true","storeID":"10501","name":"Compact Fluorescent Bulb","parentCatalogGroupID":["10001_13","10501_13"],"manufacturer":"Glomor Lighting","groupingProperties":{"groupCount":9,"groupOwner":"13842","groupHero":"13842"},"price":[{"minimumValue":{"value":"16.5"},"usage":"Display","description":"L","currency":"USD","value":"16.5","maximumValue":{"value":"16.5"}},{"minimumValue":{"value":"14.55"},"usage":"Offer","description":"I","currency":"USD","value":"14.55","maximumValue":{"value":"14.55"}}],"attributes":[{"identifier":"hardware_lightingVolts","sequence":".00000","storeDisplay":false,"values":[{"identifier":"0","sequence":".00000","unitOfMeasure":"","unitID":"","value":"0","uniqueID":"0"}],"usage":"Defining","displayable":true,"name":"Volts","facetable":false,"comparable":true,"searchable":false,"uniqueID":"7000000000000000169"},{"identifier":"Bulb type","sequence":".00000","storeDisplay":false,"values":[{"identifier":"Fluorescent_LA042_4201","sequence":"1.00000","unitOfMeasure":"","unitID":"","value":"Fluorescent","uniqueID":"7000000000000002916"}],"usage":"Descriptive","displayable":true,"name":"Bulb type","facetable":false,"comparable":true,"searchable":false,"uniqueID":"7000000000000000176"},{"identifier":"Package quantity","sequence":"1.00000","storeDisplay":false,"values":[{"identifier":"4_LA042_4201","sequence":"1.00000","unitOfMeasure":"","unitID":"","value":"4","uniqueID":"7000000000000002907"}],"usage":"Descriptive","displayable":true,"name":"Package quantity","facetable":false,"comparable":true,"searchable":false,"uniqueID":"7000000000000000145"},{"identifier":"hardware_lightingFinish","sequence":"1.00000","storeDisplay":false,"values":[{"identifier":"0","sequence":".00000","unitOfMeasure":"","unitID":"","value":"0","uniqueID":"0"}],"usage":"Defining","displayable":true,"name":"Finish","facetable":false,"comparable":true,"searchable":false,"uniqueID":"7000000000000000171"},{"identifier":"hardware_lightingWatts","sequence":"2.00000","storeDisplay":false,"values":[{"identifier":"0","sequence":".00000","unitOfMeasure":"","unitID":"","value":"0","uniqueID":"0"}],"usage":"Defining","displayable":true,"name":"Watts","facetable":false,"comparable":true,"searchable":false,"uniqueID":"7000000000000000170"},{"identifier":"Lumens","sequence":"2.00000","storeDisplay":false,"values":[{"identifier":"1000_LA042_4201","sequence":"1.00000","unitOfMeasure":"","unitID":"","value":"1000","uniqueID":"7000000000000002889"}],"usage":"Descriptive","displayable":true,"name":"Lumens","facetable":false,"comparable":true,"searchable":false,"uniqueID":"7000000000000000174"},{"identifier":"Base type","sequence":"3.00000","storeDisplay":false,"values":[{"identifier":"Medium screw (E26)_LA042_4201","sequence":"1.00000","unitOfMeasure":"","unitID":"","image1":"images/catalog/hardware/facets/basestyles/bulb_basestyle_medium_screw.png","value":"Medium screw (E26)","image1path":"/wcsstore/ExtendedSitesCatalogAssetStore/images/catalog/hardware/facets/basestyles/bulb_basestyle_medium_screw.png","uniqueID":"7000000000000002898"}],"usage":"Descriptive","displayable":true,"name":"Base type","facetable":false,"comparable":true,"searchable":false,"uniqueID":"7000000000000000175"},{"identifier":"Bulb shape","sequence":"4.00000","storeDisplay":false,"values":[{"identifier":"Spiral_LA042_4201","sequence":"1.00000","unitOfMeasure":"","unitID":"","image1":"images/catalog/hardware/facets/shapes/bulb_shape_spiral.png","value":"Spiral","image1path":"/wcsstore/ExtendedSitesCatalogAssetStore/images/catalog/hardware/facets/shapes/bulb_shape_spiral.png","uniqueID":"7000000000000002880"}],"usage":"Descriptive","displayable":true,"name":"Bulb shape","facetable":false,"comparable":true,"searchable":false,"uniqueID":"7000000000000000173"},{"identifier":"Bulb width","sequence":"5.00000","storeDisplay":false,"values":[{"identifier":"2 5/16\"_LA042_4201","sequence":"1.00000","unitOfMeasure":"","unitID":"","value":"2 5/16\"","uniqueID":"7000000000000002871"}],"usage":"Descriptive","displayable":true,"name":"Bulb width","facetable":false,"comparable":true,"searchable":false,"uniqueID":"7000000000000000172"}]},{"hasSingleSKU":false,"resourceId":"https://aas129.watsoncommerce.ibm.com/search/resources/store/1/productview/byId/13851","uniqueID":"13851","partNumber":"LA042_4202","shortDescription":"Screw-in bulb with elegant pointed tip","catalogEntryTypeCode":"ProductBean","thumbnail":"https://my4.digitalexperience.ibm.com/30817b50-78a2-4463-b5e2-2d7c39231327/dxdam/ExtendedSitesCatalogAssetStore/images/catalog/hardware/lighting/fla42_lighting/200x310/la042_4202.jpg","buyable":"true","storeID":"10501","name":"Medium-base Chandelier Bulb","parentCatalogGroupID":["10001_13","10501_13"],"manufacturer":"Pirini Inc.","groupingProperties":{"groupCount":3,"groupOwner":"13851","groupHero":"13851"},"price":[{"minimumValue":{"value":"2.97"},"usage":"Display","description":"L","currency":"USD","value":"2.97","maximumValue":{"value":"2.97"}},{"minimumValue":{"value":"2.37"},"usage":"Offer","description":"I","currency":"USD","value":"2.37","maximumValue":{"value":"2.37"}}],"attributes":[{"identifier":"hardware_lightingVolts","sequence":".00000","storeDisplay":false,"values":[{"identifier":"0","sequence":".00000","unitOfMeasure":"","unitID":"","value":"0","uniqueID":"0"}],"usage":"Defining","displayable":true,"name":"Volts","facetable":false,"comparable":true,"searchable":false,"uniqueID":"7000000000000000169"},{"identifier":"Bulb type","sequence":".00000","storeDisplay":false,"values":[{"identifier":"Incandescent_LA042_4202","sequence":"2.00000","unitOfMeasure":"","unitID":"","value":"Incandescent","uniqueID":"7000000000000002917"}],"usage":"Descriptive","displayable":true,"name":"Bulb type","facetable":false,"comparable":true,"searchable":false,"uniqueID":"7000000000000000176"},{"identifier":"Package quantity","sequence":"1.00000","storeDisplay":false,"values":[{"identifier":"2_LA042_4202","sequence":"2.00000","unitOfMeasure":"","unitID":"","value":"2","uniqueID":"7000000000000002908"}],"usage":"Descriptive","displayable":true,"name":"Package quantity","facetable":false,"comparable":true,"searchable":false,"uniqueID":"7000000000000000145"},{"identifier":"hardware_lightingWatts","sequence":"1.00000","storeDisplay":false,"values":[{"identifier":"0","sequence":".00000","unitOfMeasure":"","unitID":"","value":"0","uniqueID":"0"}],"usage":"Defining","displayable":true,"name":"Watts","facetable":false,"comparable":true,"searchable":false,"uniqueID":"7000000000000000170"},{"identifier":"Lumens","sequence":"2.00000","storeDisplay":false,"values":[{"identifier":"320_LA042_4202","sequence":"2.00000","unitOfMeasure":"","unitID":"","value":"320","uniqueID":"7000000000000002890"}],"usage":"Descriptive","displayable":true,"name":"Lumens","facetable":false,"comparable":true,"searchable":false,"uniqueID":"7000000000000000174"},{"identifier":"Base type","sequence":"3.00000","storeDisplay":false,"values":[{"identifier":"Medium screw (E26)_LA042_4202","sequence":"2.00000","unitOfMeasure":"","unitID":"","image1":"images/catalog/hardware/facets/basestyles/bulb_basestyle_medium_screw.png","value":"Medium screw (E26)","image1path":"/wcsstore/ExtendedSitesCatalogAssetStore/images/catalog/hardware/facets/basestyles/bulb_basestyle_medium_screw.png","uniqueID":"7000000000000002899"}],"usage":"Descriptive","displayable":true,"name":"Base type","facetable":false,"comparable":true,"searchable":false,"uniqueID":"7000000000000000175"},{"identifier":"Bulb shape","sequence":"4.00000","storeDisplay":false,"values":[{"identifier":"Pointed_LA042_4202","sequence":"2.00000","unitOfMeasure":"","unitID":"","image1":"images/catalog/hardware/facets/shapes/bulb_shape_pointed.png","value":"Pointed","image1path":"/wcsstore/ExtendedSitesCatalogAssetStore/images/catalog/hardware/facets/shapes/bulb_shape_pointed.png","uniqueID":"7000000000000002881"}],"usage":"Descriptive","displayable":true,"name":"Bulb shape","facetable":false,"comparable":true,"searchable":false,"uniqueID":"7000000000000000173"},{"identifier":"Bulb width","sequence":"5.00000","storeDisplay":false,"values":[{"identifier":"1 \"_LA042_4202","sequence":"2.00000","unitOfMeasure":"","unitID":"","value":"1 \"","uniqueID":"7000000000000002872"}],"usage":"Descriptive","displayable":true,"name":"Bulb width","facetable":false,"comparable":true,"searchable":false,"uniqueID":"7000000000000000172"}]},{"hasSingleSKU":false,"resourceId":"https://aas129.watsoncommerce.ibm.com/search/resources/store/1/productview/byId/13854","uniqueID":"13854","partNumber":"LA042_4203","shortDescription":"Standard household bulb with varying wattage","catalogEntryTypeCode":"ProductBean","thumbnail":"https://my4.digitalexperience.ibm.com/30817b50-78a2-4463-b5e2-2d7c39231327/dxdam/ExtendedSitesCatalogAssetStore/images/catalog/hardware/lighting/fla42_lighting/200x310/la042_4203.jpg","buyable":"true","storeID":"10501","name":"Standard Incandescent Bulb","parentCatalogGroupID":["10001_13","10501_13"],"manufacturer":"Baddeck Worldwide","groupingProperties":{"groupCount":17,"groupOwner":"13854","groupHero":"13854"},"price":[{"minimumValue":{"value":"5.0"},"usage":"Display","description":"L","currency":"USD","value":"5.0","maximumValue":{"value":"5.0"}},{"minimumValue":{"value":"3.65"},"usage":"Offer","description":"I","currency":"USD","value":"3.65","maximumValue":{"value":"3.65"}}],"attributes":[{"identifier":"hardware_lightingVolts","sequence":".00000","storeDisplay":false,"values":[{"identifier":"0","sequence":".00000","unitOfMeasure":"","unitID":"","value":"0","uniqueID":"0"}],"usage":"Defining","displayable":true,"name":"Volts","facetable":false,"comparable":true,"searchable":false,"uniqueID":"7000000000000000169"},{"identifier":"Bulb type","sequence":".00000","storeDisplay":false,"values":[{"identifier":"Incandescent_LA042_4203","sequence":"3.00000","unitOfMeasure":"","unitID":"","value":"Incandescent","uniqueID":"7000000000000002918"}],"usage":"Descriptive","displayable":true,"name":"Bulb type","facetable":false,"comparable":true,"searchable":false,"uniqueID":"7000000000000000176"},{"identifier":"Package quantity","sequence":"1.00000","storeDisplay":false,"values":[{"identifier":"2_LA042_4203","sequence":"3.00000","unitOfMeasure":"","unitID":"","value":"2","uniqueID":"7000000000000002909"}],"usage":"Descriptive","displayable":true,"name":"Package quantity","facetable":false,"comparable":true,"searchable":false,"uniqueID":"7000000000000000145"},{"identifier":"hardware_lightingFinish","sequence":"1.00000","storeDisplay":false,"values":[{"identifier":"0","sequence":".00000","unitOfMeasure":"","unitID":"","value":"0","uniqueID":"0"}],"usage":"Defining","displayable":true,"name":"Finish","facetable":false,"comparable":true,"searchable":false,"uniqueID":"7000000000000000171"},{"identifier":"hardware_lightingWatts","sequence":"2.00000","storeDisplay":false,"values":[{"identifier":"0","sequence":".00000","unitOfMeasure":"","unitID":"","value":"0","uniqueID":"0"}],"usage":"Defining","displayable":true,"name":"Watts","facetable":false,"comparable":true,"searchable":false,"uniqueID":"7000000000000000170"},{"identifier":"Lumens","sequence":"2.00000","storeDisplay":false,"values":[{"identifier":"160_LA042_4203","sequence":"3.00000","unitOfMeasure":"","unitID":"","value":"160","uniqueID":"7000000000000002891"}],"usage":"Descriptive","displayable":true,"name":"Lumens","facetable":false,"comparable":true,"searchable":false,"uniqueID":"7000000000000000174"},{"identifier":"Base type","sequence":"3.00000","storeDisplay":false,"values":[{"identifier":"Medium screw (E26)_LA042_4203","sequence":"3.00000","unitOfMeasure":"","unitID":"","image1":"images/catalog/hardware/facets/basestyles/bulb_basestyle_medium_screw.png","value":"Medium screw (E26)","image1path":"/wcsstore/ExtendedSitesCatalogAssetStore/images/catalog/hardware/facets/basestyles/bulb_basestyle_medium_screw.png","uniqueID":"7000000000000002900"}],"usage":"Descriptive","displayable":true,"name":"Base type","facetable":false,"comparable":true,"searchable":false,"uniqueID":"7000000000000000175"},{"identifier":"Bulb shape","sequence":"4.00000","storeDisplay":false,"values":[{"identifier":"General_LA042_4203","sequence":"3.00000","unitOfMeasure":"","unitID":"","image1":"images/catalog/hardware/facets/shapes/bulb_shape_general.png","value":"General","image1path":"/wcsstore/ExtendedSitesCatalogAssetStore/images/catalog/hardware/facets/shapes/bulb_shape_general.png","uniqueID":"7000000000000002882"}],"usage":"Descriptive","displayable":true,"name":"Bulb shape","facetable":false,"comparable":true,"searchable":false,"uniqueID":"7000000000000000173"},{"identifier":"Bulb width","sequence":"5.00000","storeDisplay":false,"values":[{"identifier":"2 3/8\"_LA042_4203","sequence":"3.00000","unitOfMeasure":"","unitID":"","value":"2 3/8\"","uniqueID":"7000000000000002873"}],"usage":"Descriptive","displayable":true,"name":"Bulb width","facetable":false,"comparable":true,"searchable":false,"uniqueID":"7000000000000000172"}]},{"hasSingleSKU":true,"resourceId":"https://aas129.watsoncommerce.ibm.com/search/resources/store/1/productview/byId/13871","uniqueID":"13871","partNumber":"LA042_4204","singleSKUCatalogEntryID":"13872","shortDescription":"Black light blue fluorescent bulb with screw-in base","catalogEntryTypeCode":"ProductBean","thumbnail":"https://my4.digitalexperience.ibm.com/30817b50-78a2-4463-b5e2-2d7c39231327/dxdam/ExtendedSitesCatalogAssetStore/images/catalog/hardware/lighting/fla42_lighting/200x310/la042_4204.jpg","buyable":"true","storeID":"10501","name":"Dual-tube Ultraviolet Bulb","parentCatalogGroupID":["10001_13","10501_13"],"manufacturer":"Pirini Inc.","groupingProperties":{"groupCount":2,"groupOwner":"13871","groupHero":"13871"},"price":[{"minimumValue":{"value":"17.99"},"usage":"Display","description":"L","currency":"USD","value":"17.99","maximumValue":{"value":"17.99"}},{"minimumValue":{"value":"15.77"},"usage":"Offer","description":"I","currency":"USD","value":"15.77","maximumValue":{"value":"15.77"}}],"attributes":[{"identifier":"hardware_lightingVolts","sequence":".00000","storeDisplay":false,"values":[{"identifier":"0","sequence":".00000","unitOfMeasure":"","unitID":"","value":"0","uniqueID":"0"}],"usage":"Defining","displayable":true,"name":"Volts","facetable":false,"comparable":true,"searchable":false,"uniqueID":"7000000000000000169"},{"identifier":"Bulb type","sequence":".00000","storeDisplay":false,"values":[{"identifier":"Ultraviolet_LA042_4204","sequence":"4.00000","unitOfMeasure":"","unitID":"","value":"Ultraviolet","uniqueID":"7000000000000002919"}],"usage":"Descriptive","displayable":true,"name":"Bulb type","facetable":false,"comparable":true,"searchable":false,"uniqueID":"7000000000000000176"},{"identifier":"Package quantity","sequence":"1.00000","storeDisplay":false,"values":[{"identifier":"1_LA042_4204","sequence":"4.00000","unitOfMeasure":"","unitID":"","value":"1","uniqueID":"7000000000000002910"}],"usage":"Descriptive","displayable":true,"name":"Package quantity","facetable":false,"comparable":true,"searchable":false,"uniqueID":"7000000000000000145"},{"identifier":"hardware_lightingWatts","sequence":"1.00000","storeDisplay":false,"values":[{"identifier":"0","sequence":".00000","unitOfMeasure":"","unitID":"","value":"0","uniqueID":"0"}],"usage":"Defining","displayable":true,"name":"Watts","facetable":false,"comparable":true,"searchable":false,"uniqueID":"7000000000000000170"},{"identifier":"Lumens","sequence":"2.00000","storeDisplay":false,"values":[{"identifier":"160_LA042_4204","sequence":"4.00000","unitOfMeasure":"","unitID":"","value":"160","uniqueID":"7000000000000002892"}],"usage":"Descriptive","displayable":true,"name":"Lumens","facetable":false,"comparable":true,"searchable":false,"uniqueID":"7000000000000000174"},{"identifier":"Base type","sequence":"3.00000","storeDisplay":false,"values":[{"identifier":"Medium screw (E26)_LA042_4204","sequence":"4.00000","unitOfMeasure":"","unitID":"","image1":"images/catalog/hardware/facets/basestyles/bulb_basestyle_medium_screw.png","value":"Medium screw (E26)","image1path":"/wcsstore/ExtendedSitesCatalogAssetStore/images/catalog/hardware/facets/basestyles/bulb_basestyle_medium_screw.png","uniqueID":"7000000000000002901"}],"usage":"Descriptive","displayable":true,"name":"Base type","facetable":false,"comparable":true,"searchable":false,"uniqueID":"7000000000000000175"},{"identifier":"Bulb shape","sequence":"4.00000","storeDisplay":false,"values":[{"identifier":"Dual tube_LA042_4204","sequence":"4.00000","unitOfMeasure":"","unitID":"","image1":"images/catalog/hardware/facets/shapes/bulb_shape_dualtube.png","value":"Dual tube","image1path":"/wcsstore/ExtendedSitesCatalogAssetStore/images/catalog/hardware/facets/shapes/bulb_shape_dualtube.png","uniqueID":"7000000000000002883"}],"usage":"Descriptive","displayable":true,"name":"Bulb shape","facetable":false,"comparable":true,"searchable":false,"uniqueID":"7000000000000000173"},{"identifier":"Bulb width","sequence":"5.00000","storeDisplay":false,"values":[{"identifier":"7/8\"_LA042_4204","sequence":"4.00000","unitOfMeasure":"","unitID":"","value":"7/8\"","uniqueID":"7000000000000002874"}],"usage":"Descriptive","displayable":true,"name":"Bulb width","facetable":false,"comparable":true,"searchable":false,"uniqueID":"7000000000000000172"}]},{"hasSingleSKU":false,"resourceId":"https://aas129.watsoncommerce.ibm.com/search/resources/store/1/productview/byId/13873","uniqueID":"13873","partNumber":"LA042_4205","shortDescription":"Dimmable energy-saving floodlight bulb","catalogEntryTypeCode":"ProductBean","thumbnail":"https://my4.digitalexperience.ibm.com/30817b50-78a2-4463-b5e2-2d7c39231327/dxdam/ExtendedSitesCatalogAssetStore/images/catalog/hardware/lighting/fla42_lighting/200x310/la042_4205.jpg","buyable":"true","storeID":"10501","name":"Screw-in LED Bulb","parentCatalogGroupID":["10001_13","10501_13"],"manufacturer":"Baddeck Worldwide","groupingProperties":{"groupCount":5,"groupOwner":"13873","groupHero":"13873"},"price":[{"minimumValue":{"value":"16.5"},"usage":"Display","description":"L","currency":"USD","value":"16.5","maximumValue":{"value":"16.5"}},{"minimumValue":{"value":"13.65"},"usage":"Offer","description":"I","currency":"USD","value":"13.65","maximumValue":{"value":"13.65"}}],"attributes":[{"identifier":"hardware_lightingVolts","sequence":".00000","storeDisplay":false,"values":[{"identifier":"0","sequence":".00000","unitOfMeasure":"","unitID":"","value":"0","uniqueID":"0"}],"usage":"Defining","displayable":true,"name":"Volts","facetable":false,"comparable":true,"searchable":false,"uniqueID":"7000000000000000169"},{"identifier":"Bulb type","sequence":".00000","storeDisplay":false,"values":[{"identifier":"LED_LA042_4205","sequence":"5.00000","unitOfMeasure":"","unitID":"","value":"LED","uniqueID":"7000000000000002920"}],"usage":"Descriptive","displayable":true,"name":"Bulb type","facetable":false,"comparable":true,"searchable":false,"uniqueID":"7000000000000000176"},{"identifier":"Package quantity","sequence":"1.00000","storeDisplay":false,"values":[{"identifier":"1_LA042_4205","sequence":"5.00000","unitOfMeasure":"","unitID":"","value":"1","uniqueID":"7000000000000002911"}],"usage":"Descriptive","displayable":true,"name":"Package quantity","facetable":false,"comparable":true,"searchable":false,"uniqueID":"7000000000000000145"},{"identifier":"hardware_lightingFinish","sequence":"1.00000","storeDisplay":false,"values":[{"identifier":"0","sequence":".00000","unitOfMeasure":"","unitID":"","value":"0","uniqueID":"0"}],"usage":"Defining","displayable":true,"name":"Finish","facetable":false,"comparable":true,"searchable":false,"uniqueID":"7000000000000000171"},{"identifier":"hardware_lightingWatts","sequence":"2.00000","storeDisplay":false,"values":[{"identifier":"0","sequence":".00000","unitOfMeasure":"","unitID":"","value":"0","uniqueID":"0"}],"usage":"Defining","displayable":true,"name":"Watts","facetable":false,"comparable":true,"searchable":false,"uniqueID":"7000000000000000170"},{"identifier":"Lumens","sequence":"2.00000","storeDisplay":false,"values":[{"identifier":"580_LA042_4205","sequence":"5.00000","unitOfMeasure":"","unitID":"","value":"580","uniqueID":"7000000000000002893"}],"usage":"Descriptive","displayable":true,"name":"Lumens","facetable":false,"comparable":true,"searchable":false,"uniqueID":"7000000000000000174"},{"identifier":"Base type","sequence":"3.00000","storeDisplay":false,"values":[{"identifier":"Medium screw (E26)_LA042_4205","sequence":"5.00000","unitOfMeasure":"","unitID":"","image1":"images/catalog/hardware/facets/basestyles/bulb_basestyle_medium_screw.png","value":"Medium screw (E26)","image1path":"/wcsstore/ExtendedSitesCatalogAssetStore/images/catalog/hardware/facets/basestyles/bulb_basestyle_medium_screw.png","uniqueID":"7000000000000002902"}],"usage":"Descriptive","displayable":true,"name":"Base type","facetable":false,"comparable":true,"searchable":false,"uniqueID":"7000000000000000175"},{"identifier":"Bulb shape","sequence":"4.00000","storeDisplay":false,"values":[{"identifier":"Parabolic_LA042_4205","sequence":"5.00000","unitOfMeasure":"","unitID":"","image1":"images/catalog/hardware/facets/shapes/bulb_shape_parabolic.png","value":"Parabolic","image1path":"/wcsstore/ExtendedSitesCatalogAssetStore/images/catalog/hardware/facets/shapes/bulb_shape_parabolic.png","uniqueID":"7000000000000002884"}],"usage":"Descriptive","displayable":true,"name":"Bulb shape","facetable":false,"comparable":true,"searchable":false,"uniqueID":"7000000000000000173"},{"identifier":"Bulb width","sequence":"5.00000","storeDisplay":false,"values":[{"identifier":"2 3/8\"_LA042_4205","sequence":"5.00000","unitOfMeasure":"","unitID":"","value":"2 3/8\"","uniqueID":"7000000000000002875"}],"usage":"Descriptive","displayable":true,"name":"Bulb width","facetable":false,"comparable":true,"searchable":false,"uniqueID":"7000000000000000172"}]},{"hasSingleSKU":false,"resourceId":"https://aas129.watsoncommerce.ibm.com/search/resources/store/1/productview/byId/13878","uniqueID":"13878","partNumber":"LA042_4206","shortDescription":"Multifaceted reflector (MR16) bulb that produces a wide beam of white light","catalogEntryTypeCode":"ProductBean","thumbnail":"https://my4.digitalexperience.ibm.com/30817b50-78a2-4463-b5e2-2d7c39231327/dxdam/ExtendedSitesCatalogAssetStore/images/catalog/hardware/lighting/fla42_lighting/200x310/la042_4206.jpg","buyable":"true","storeID":"10501","name":"Halogen Floodlight Bulb","parentCatalogGroupID":["10001_13","10501_13"],"manufacturer":"Baddeck Worldwide","groupingProperties":{"groupCount":5,"groupOwner":"13878","groupHero":"13878"},"price":[{"minimumValue":{"value":"19.0"},"usage":"Display","description":"L","currency":"USD","value":"19.0","maximumValue":{"value":"19.0"}},{"minimumValue":{"value":"17.65"},"usage":"Offer","description":"I","currency":"USD","value":"17.65","maximumValue":{"value":"17.65"}}],"attributes":[{"identifier":"hardware_lightingVolts","sequence":".00000","storeDisplay":false,"values":[{"identifier":"0","sequence":".00000","unitOfMeasure":"","unitID":"","value":"0","uniqueID":"0"}],"usage":"Defining","displayable":true,"name":"Volts","facetable":false,"comparable":true,"searchable":false,"uniqueID":"7000000000000000169"},{"identifier":"Bulb type","sequence":".00000","storeDisplay":false,"values":[{"identifier":"Halogen_LA042_4206","sequence":"6.00000","unitOfMeasure":"","unitID":"","value":"Halogen","uniqueID":"7000000000000002921"}],"usage":"Descriptive","displayable":true,"name":"Bulb type","facetable":false,"comparable":true,"searchable":false,"uniqueID":"7000000000000000176"},{"identifier":"Package quantity","sequence":"1.00000","storeDisplay":false,"values":[{"identifier":"10_LA042_4206","sequence":"6.00000","unitOfMeasure":"","unitID":"","value":"10","uniqueID":"7000000000000002912"}],"usage":"Descriptive","displayable":true,"name":"Package quantity","facetable":false,"comparable":true,"searchable":false,"uniqueID":"7000000000000000145"},{"identifier":"hardware_lightingWatts","sequence":"1.00000","storeDisplay":false,"values":[{"identifier":"0","sequence":".00000","unitOfMeasure":"","unitID":"","value":"0","uniqueID":"0"}],"usage":"Defining","displayable":true,"name":"Watts","facetable":false,"comparable":true,"searchable":false,"uniqueID":"7000000000000000170"},{"identifier":"Lumens","sequence":"2.00000","storeDisplay":false,"values":[{"identifier":"900_LA042_4206","sequence":"6.00000","unitOfMeasure":"","unitID":"","value":"900","uniqueID":"7000000000000002894"}],"usage":"Descriptive","displayable":true,"name":"Lumens","facetable":false,"comparable":true,"searchable":false,"uniqueID":"7000000000000000174"},{"identifier":"Base type","sequence":"3.00000","storeDisplay":false,"values":[{"identifier":"2-pin_LA042_4206","sequence":"6.00000","unitOfMeasure":"","unitID":"","image1":"images/catalog/hardware/facets/basestyles/bulb_basestyle_2pins.png","value":"2-pin","image1path":"/wcsstore/ExtendedSitesCatalogAssetStore/images/catalog/hardware/facets/basestyles/bulb_basestyle_2pins.png","uniqueID":"7000000000000002903"}],"usage":"Descriptive","displayable":true,"name":"Base type","facetable":false,"comparable":true,"searchable":false,"uniqueID":"7000000000000000175"},{"identifier":"Bulb shape","sequence":"4.00000","storeDisplay":false,"values":[{"identifier":"Parabolic_LA042_4206","sequence":"6.00000","unitOfMeasure":"","unitID":"","image1":"images/catalog/hardware/facets/shapes/bulb_shape_parabolic.png","value":"Parabolic","image1path":"/wcsstore/ExtendedSitesCatalogAssetStore/images/catalog/hardware/facets/shapes/bulb_shape_parabolic.png","uniqueID":"7000000000000002885"}],"usage":"Descriptive","displayable":true,"name":"Bulb shape","facetable":false,"comparable":true,"searchable":false,"uniqueID":"7000000000000000173"},{"identifier":"Bulb width","sequence":"5.00000","storeDisplay":false,"values":[{"identifier":"2\"_LA042_4206","sequence":"6.00000","unitOfMeasure":"","unitID":"","value":"2\"","uniqueID":"7000000000000002876"}],"usage":"Descriptive","displayable":true,"name":"Bulb width","facetable":false,"comparable":true,"searchable":false,"uniqueID":"7000000000000000172"}]},{"hasSingleSKU":false,"resourceId":"https://aas129.watsoncommerce.ibm.com/search/resources/store/1/productview/byId/13883","uniqueID":"13883","partNumber":"LA042_4207","shortDescription":"Flame-shaped screw-in bulb with clear or frosted finish","catalogEntryTypeCode":"ProductBean","thumbnail":"https://my4.digitalexperience.ibm.com/30817b50-78a2-4463-b5e2-2d7c39231327/dxdam/ExtendedSitesCatalogAssetStore/images/catalog/hardware/lighting/fla42_lighting/200x310/la042_4207.jpg","buyable":"true","storeID":"10501","name":"Candelabra Incandescent Bulb","parentCatalogGroupID":["10001_13","10501_13"],"manufacturer":"Glomor Lighting","groupingProperties":{"groupCount":9,"groupOwner":"13883","groupHero":"13883"},"price":[{"minimumValue":{"value":"9.0"},"usage":"Display","description":"L","currency":"USD","value":"9.0","maximumValue":{"value":"9.0"}},{"minimumValue":{"value":"7.61"},"usage":"Offer","description":"I","currency":"USD","value":"7.61","maximumValue":{"value":"7.61"}}],"attributes":[{"identifier":"hardware_lightingVolts","sequence":".00000","storeDisplay":false,"values":[{"identifier":"0","sequence":".00000","unitOfMeasure":"","unitID":"","value":"0","uniqueID":"0"}],"usage":"Defining","displayable":true,"name":"Volts","facetable":false,"comparable":true,"searchable":false,"uniqueID":"7000000000000000169"},{"identifier":"Bulb type","sequence":".00000","storeDisplay":false,"values":[{"identifier":"Incandescent_LA042_4207","sequence":"7.00000","unitOfMeasure":"","unitID":"","value":"Incandescent","uniqueID":"7000000000000002922"}],"usage":"Descriptive","displayable":true,"name":"Bulb type","facetable":false,"comparable":true,"searchable":false,"uniqueID":"7000000000000000176"},{"identifier":"Package quantity","sequence":"1.00000","storeDisplay":false,"values":[{"identifier":"10_LA042_4207","sequence":"7.00000","unitOfMeasure":"","unitID":"","value":"10","uniqueID":"7000000000000002913"}],"usage":"Descriptive","displayable":true,"name":"Package quantity","facetable":false,"comparable":true,"searchable":false,"uniqueID":"7000000000000000145"},{"identifier":"hardware_lightingFinish","sequence":"1.00000","storeDisplay":false,"values":[{"identifier":"0","sequence":".00000","unitOfMeasure":"","unitID":"","value":"0","uniqueID":"0"}],"usage":"Defining","displayable":true,"name":"Finish","facetable":false,"comparable":true,"searchable":false,"uniqueID":"7000000000000000171"},{"identifier":"hardware_lightingWatts","sequence":"2.00000","storeDisplay":false,"values":[{"identifier":"0","sequence":".00000","unitOfMeasure":"","unitID":"","value":"0","uniqueID":"0"}],"usage":"Defining","displayable":true,"name":"Watts","facetable":false,"comparable":true,"searchable":false,"uniqueID":"7000000000000000170"},{"identifier":"Lumens","sequence":"2.00000","storeDisplay":false,"values":[{"identifier":"30_LA042_4207","sequence":"7.00000","unitOfMeasure":"","unitID":"","value":"30","uniqueID":"7000000000000002895"}],"usage":"Descriptive","displayable":true,"name":"Lumens","facetable":false,"comparable":true,"searchable":false,"uniqueID":"7000000000000000174"},{"identifier":"Base type","sequence":"3.00000","storeDisplay":false,"values":[{"identifier":"Candelabra_LA042_4207","sequence":"7.00000","unitOfMeasure":"","unitID":"","image1":"images/catalog/hardware/facets/basestyles/bulb_basestyle_medium_candelabra.png","value":"Candelabra","image1path":"/wcsstore/ExtendedSitesCatalogAssetStore/images/catalog/hardware/facets/basestyles/bulb_basestyle_medium_candelabra.png","uniqueID":"7000000000000002904"}],"usage":"Descriptive","displayable":true,"name":"Base type","facetable":false,"comparable":true,"searchable":false,"uniqueID":"7000000000000000175"},{"identifier":"Bulb shape","sequence":"4.00000","storeDisplay":false,"values":[{"identifier":"Flame_LA042_4207","sequence":"7.00000","unitOfMeasure":"","unitID":"","image1":"images/catalog/hardware/facets/shapes/bulb_shape_flame.png","value":"Flame","image1path":"/wcsstore/ExtendedSitesCatalogAssetStore/images/catalog/hardware/facets/shapes/bulb_shape_flame.png","uniqueID":"7000000000000002886"}],"usage":"Descriptive","displayable":true,"name":"Bulb shape","facetable":false,"comparable":true,"searchable":false,"uniqueID":"7000000000000000173"},{"identifier":"Bulb width","sequence":"5.00000","storeDisplay":false,"values":[{"identifier":"7/8\"_LA042_4207","sequence":"7.00000","unitOfMeasure":"","unitID":"","value":"7/8\"","uniqueID":"7000000000000002877"}],"usage":"Descriptive","displayable":true,"name":"Bulb width","facetable":false,"comparable":true,"searchable":false,"uniqueID":"7000000000000000172"}]},{"hasSingleSKU":false,"resourceId":"https://aas129.watsoncommerce.ibm.com/search/resources/store/1/productview/byId/13892","uniqueID":"13892","partNumber":"LA042_4209","shortDescription":"Shatter-resistant T12 fluorescent bulb with 2-pin base","catalogEntryTypeCode":"ProductBean","thumbnail":"https://my4.digitalexperience.ibm.com/30817b50-78a2-4463-b5e2-2d7c39231327/dxdam/ExtendedSitesCatalogAssetStore/images/catalog/hardware/lighting/fla42_lighting/200x310/la042_4209.jpg","buyable":"true","storeID":"10501","name":"Linear Fluorescent Bulb","parentCatalogGroupID":["10001_13","10501_13"],"manufacturer":"Glomor Lighting","groupingProperties":{"groupCount":19,"groupOwner":"13892","groupHero":"13892"},"price":[{"minimumValue":{"value":"40.5"},"usage":"Display","description":"L","currency":"USD","value":"40.5","maximumValue":{"value":"40.5"}},{"minimumValue":{"value":"37.25"},"usage":"Offer","description":"I","currency":"USD","value":"37.25","maximumValue":{"value":"37.25"}}],"attributes":[{"identifier":"hardware_lightingVolts","sequence":".00000","storeDisplay":false,"values":[{"identifier":"0","sequence":".00000","unitOfMeasure":"","unitID":"","value":"0","uniqueID":"0"}],"usage":"Defining","displayable":true,"name":"Volts","facetable":false,"comparable":true,"searchable":false,"uniqueID":"7000000000000000169"},{"identifier":"Bulb type","sequence":".00000","storeDisplay":false,"values":[{"identifier":"Fluorescent_LA042_4209","sequence":"8.00000","unitOfMeasure":"","unitID":"","value":"Fluorescent","uniqueID":"7000000000000002923"}],"usage":"Descriptive","displayable":true,"name":"Bulb type","facetable":false,"comparable":true,"searchable":false,"uniqueID":"7000000000000000176"},{"identifier":"Package quantity","sequence":"1.00000","storeDisplay":false,"values":[{"identifier":"6_LA042_4209","sequence":"8.00000","unitOfMeasure":"","unitID":"","value":"6","uniqueID":"7000000000000002914"}],"usage":"Descriptive","displayable":true,"name":"Package quantity","facetable":false,"comparable":true,"searchable":false,"uniqueID":"7000000000000000145"},{"identifier":"hardware_lightingLength","sequence":"1.00000","storeDisplay":false,"values":[{"identifier":"0","sequence":".00000","unitOfMeasure":"","unitID":"","value":"0","uniqueID":"0"}],"usage":"Defining","displayable":true,"name":"Length","facetable":false,"comparable":true,"searchable":false,"uniqueID":"7000000000000000168"},{"identifier":"hardware_lightingWatts","sequence":"2.00000","storeDisplay":false,"values":[{"identifier":"0","sequence":".00000","unitOfMeasure":"","unitID":"","value":"0","uniqueID":"0"}],"usage":"Defining","displayable":true,"name":"Watts","facetable":false,"comparable":true,"searchable":false,"uniqueID":"7000000000000000170"},{"identifier":"Lumens","sequence":"2.00000","storeDisplay":false,"values":[{"identifier":"2550_LA042_4209","sequence":"8.00000","unitOfMeasure":"","unitID":"","value":"2550","uniqueID":"7000000000000002896"}],"usage":"Descriptive","displayable":true,"name":"Lumens","facetable":false,"comparable":true,"searchable":false,"uniqueID":"7000000000000000174"},{"identifier":"Base type","sequence":"3.00000","storeDisplay":false,"values":[{"identifier":"2-pin_LA042_4209","sequence":"8.00000","unitOfMeasure":"","unitID":"","image1":"images/catalog/hardware/facets/basestyles/bulb_basestyle_2pins.png","value":"2-pin","image1path":"/wcsstore/ExtendedSitesCatalogAssetStore/images/catalog/hardware/facets/basestyles/bulb_basestyle_2pins.png","uniqueID":"7000000000000002905"}],"usage":"Descriptive","displayable":true,"name":"Base type","facetable":false,"comparable":true,"searchable":false,"uniqueID":"7000000000000000175"},{"identifier":"Bulb shape","sequence":"4.00000","storeDisplay":false,"values":[{"identifier":"Large tube_LA042_4209","sequence":"8.00000","unitOfMeasure":"","unitID":"","image1":"images/catalog/hardware/facets/shapes/bulb_shape_largetube.png","value":"Large tube","image1path":"/wcsstore/ExtendedSitesCatalogAssetStore/images/catalog/hardware/facets/shapes/bulb_shape_largetube.png","uniqueID":"7000000000000002887"}],"usage":"Descriptive","displayable":true,"name":"Bulb shape","facetable":false,"comparable":true,"searchable":false,"uniqueID":"7000000000000000173"},{"identifier":"Bulb width","sequence":"5.00000","storeDisplay":false,"values":[{"identifier":"1 1/2\"_LA042_4209","sequence":"8.00000","unitOfMeasure":"","unitID":"","value":"1 1/2\"","uniqueID":"7000000000000002878"}],"usage":"Descriptive","displayable":true,"name":"Bulb width","facetable":false,"comparable":true,"searchable":false,"uniqueID":"7000000000000000172"}]},{"hasSingleSKU":false,"resourceId":"https://aas129.watsoncommerce.ibm.com/search/resources/store/1/productview/byId/13911","uniqueID":"13911","partNumber":"LA042_4210","shortDescription":"Miniature glow lamp that emits an orange-red light","catalogEntryTypeCode":"ProductBean","thumbnail":"https://my4.digitalexperience.ibm.com/30817b50-78a2-4463-b5e2-2d7c39231327/dxdam/ExtendedSitesCatalogAssetStore/images/catalog/hardware/lighting/fla42_lighting/200x310/la042_4210.jpg","buyable":"true","storeID":"10501","name":"Neon Indicator Bulb","parentCatalogGroupID":["10001_13","10501_13"],"manufacturer":"Pirini Inc.","groupingProperties":{"groupCount":3,"groupOwner":"13911","groupHero":"13911"},"price":[{"minimumValue":{"value":"14.5"},"usage":"Display","description":"L","currency":"USD","value":"14.5","maximumValue":{"value":"14.5"}},{"minimumValue":{"value":"12.97"},"usage":"Offer","description":"I","currency":"USD","value":"12.97","maximumValue":{"value":"12.97"}}],"attributes":[{"identifier":"hardware_lightingVolts","sequence":".00000","storeDisplay":false,"values":[{"identifier":"0","sequence":".00000","unitOfMeasure":"","unitID":"","value":"0","uniqueID":"0"}],"usage":"Defining","displayable":true,"name":"Volts","facetable":false,"comparable":true,"searchable":false,"uniqueID":"7000000000000000169"},{"identifier":"Bulb type","sequence":".00000","storeDisplay":false,"values":[{"identifier":"Neon_LA042_4210","sequence":"9.00000","unitOfMeasure":"","unitID":"","value":"Neon","uniqueID":"7000000000000002924"}],"usage":"Descriptive","displayable":true,"name":"Bulb type","facetable":false,"comparable":true,"searchable":false,"uniqueID":"7000000000000000176"},{"identifier":"Package quantity","sequence":"1.00000","storeDisplay":false,"values":[{"identifier":"6_LA042_4210","sequence":"9.00000","unitOfMeasure":"","unitID":"","value":"6","uniqueID":"7000000000000002915"}],"usage":"Descriptive","displayable":true,"name":"Package quantity","facetable":false,"comparable":true,"searchable":false,"uniqueID":"7000000000000000145"},{"identifier":"hardware_lightingLength","sequence":"1.00000","storeDisplay":false,"values":[{"identifier":"0","sequence":".00000","unitOfMeasure":"","unitID":"","value":"0","uniqueID":"0"}],"usage":"Defining","displayable":true,"name":"Length","facetable":false,"comparable":true,"searchable":false,"uniqueID":"7000000000000000168"},{"identifier":"hardware_lightingWatts","sequence":"2.00000","storeDisplay":false,"values":[{"identifier":"0","sequence":".00000","unitOfMeasure":"","unitID":"","value":"0","uniqueID":"0"}],"usage":"Defining","displayable":true,"name":"Watts","facetable":false,"comparable":true,"searchable":false,"uniqueID":"7000000000000000170"},{"identifier":"Lumens","sequence":"2.00000","storeDisplay":false,"values":[{"identifier":"20_LA042_4210","sequence":"9.00000","unitOfMeasure":"","unitID":"","value":"20","uniqueID":"7000000000000002897"}],"usage":"Descriptive","displayable":true,"name":"Lumens","facetable":false,"comparable":true,"searchable":false,"uniqueID":"7000000000000000174"},{"identifier":"Base type","sequence":"3.00000","storeDisplay":false,"values":[{"identifier":"Wire terminal_LA042_4210","sequence":"9.00000","unitOfMeasure":"","unitID":"","image1":"images/catalog/hardware/facets/basestyles/bulb_basestyle_wireterminal.png","value":"Wire terminal","image1path":"/wcsstore/ExtendedSitesCatalogAssetStore/images/catalog/hardware/facets/basestyles/bulb_basestyle_wireterminal.png","uniqueID":"7000000000000002906"}],"usage":"Descriptive","displayable":true,"name":"Base type","facetable":false,"comparable":true,"searchable":false,"uniqueID":"7000000000000000175"},{"identifier":"Bulb shape","sequence":"4.00000","storeDisplay":false,"values":[{"identifier":"Domed_LA042_4210","sequence":"9.00000","unitOfMeasure":"","unitID":"","image1":"images/catalog/hardware/facets/shapes/bulb_shape_largetube.png","value":"Domed","image1path":"/wcsstore/ExtendedSitesCatalogAssetStore/images/catalog/hardware/facets/shapes/bulb_shape_largetube.png","uniqueID":"7000000000000002888"}],"usage":"Descriptive","displayable":true,"name":"Bulb shape","facetable":false,"comparable":true,"searchable":false,"uniqueID":"7000000000000000173"},{"identifier":"Bulb width","sequence":"5.00000","storeDisplay":false,"values":[{"identifier":"3/8\"_LA042_4210","sequence":"9.00000","unitOfMeasure":"","unitID":"","value":"3/8\"","uniqueID":"7000000000000002879"}],"usage":"Descriptive","displayable":true,"name":"Bulb width","facetable":false,"comparable":true,"searchable":false,"uniqueID":"7000000000000000172"}]}],"recordSetStartNumber":"0","resourceName":"productview","recordSetTotal":9,"recordSetTotalMatches":72,"recordSetComplete":"true","facetView":[{"value":"price_USD","name":"OfferPrice_USD","entry":[{"count":9,"label":"({* 100} 100)","value":"price_USD%3A%28%7B*+100%7D+100%29","extendedData":{"uniqueId":"1121141059910195858368584012342324948481253249484841"}},{"count":0,"label":"({100 200} 200)","value":"price_USD%3A%28%7B100+200%7D+200%29","extendedData":{"uniqueId":"11211410599101958583685840123494848325048481253250484841"}},{"count":0,"label":"({200 300} 300)","value":"price_USD%3A%28%7B200+300%7D+300%29","extendedData":{"uniqueId":"11211410599101958583685840123504848325148481253251484841"}},{"count":0,"label":"({300 400} 400)","value":"price_USD%3A%28%7B300+400%7D+400%29","extendedData":{"uniqueId":"11211410599101958583685840123514848325248481253252484841"}},{"count":0,"label":"({400 500} 500)","value":"price_USD%3A%28%7B400+500%7D+500%29","extendedData":{"uniqueId":"11211410599101958583685840123524848325348481253253484841"}},{"count":0,"label":"({500 *})","value":"price_USD%3A%28%7B500+*%7D%29","extendedData":{"uniqueId":"11211410599101958583685840123534848324212541"}}]},{"value":"mfName_ntk_cs","entry":[{"label":"Baddeck Worldwide","value":"mfName_ntk_cs%3A%22Baddeck+Worldwide%22","count":"3","extendedData":{"uniqueId":"-10026697100100101991073287111114108100119105100101"}},{"label":"Glomor Lighting","value":"mfName_ntk_cs%3A%22Glomor+Lighting%22","count":"3","extendedData":{"uniqueId":"-1002711081111091111143276105103104116105110103"}},{"label":"Pirini Inc.","value":"mfName_ntk_cs%3A%22Pirini+Inc.%22","count":"3","extendedData":{"uniqueId":"-10028010511410511010532731109946"}}],"name":"ManufacturerName","extendedData":{"allowMultipleValueSelection":"false","maximumValuesToDisplay":"20","groupId":"0","allValuesReturned":true,"fname":"Brand","keyword_search":"1","propertyname":"facet","propertyvalue":"mfName_ntk_cs","displayable":"1","facet_id":"-1000","srchattr_id":"-1002","zero_display":"0","selection":"0","group_id":"0","displaySequence":"0.0","storeent_id":"0","sortorder":"0","max_display":"20","fdesc":"The manufacturer","srchattridentifier":"_cat.ManufacturerName"}}]}