{"pagination":{"numFound":5,"pageSize":"2","pageNumber":"1"},"data":[{"partNumber":"BR-FIXT-0001","productType":"ProductBean","buyable":true,"descriptiveAttributes":["ProductDimensions/_/Product Dimensions/_/1.0/_/3\"x8\"x8\"/_/10.0","ItemWeight/_/Item Weight/_/2.0/_/10 lbs/_/1.0","Materials/_/Material/_/3.0/_/Metal, Brass/_/2.0"],"definingAttributes":["Color/_/Color/_/1.0/_/Chrome/_/1.0"],"store":"Stockholm","manufacturer":"Stockholm","parentCategoryPaths":["/Bath/Fixtures"],"displayName":"Single Handle Bath Faucet","shortDescription":"A contemporary bath faucet that fits in all spaces. Perfect for creating a cozy powder room atmosphere.","urlName":"Single Handle Bath Faucet","price":{"usage":"Display","value":35.0,"description":"L","currency":"USD","minimumValue":35.0,"maximumValue":35.0},"parentCategories":["Fixtures"]},{"partNumber":"BR-FIXT-0002","productType":"ProductBean","buyable":true,"descriptiveAttributes":["ProductDimensions/_/Product Dimensions/_/1.0/_/6\"x18\"x12\"/_/11.0","ItemWeight/_/Item Weight/_/2.0/_/15 lbs/_/6.0","Materials/_/Material/_/3.0/_/Metal, Brass/_/2.0"],"definingAttributes":["Color/_/Color/_/1.0/_/Chrome/_/1.0"],"store":"Stockholm","manufacturer":"Bender Home Fashions","parentCategoryPaths":["/Bath/Fixtures"],"displayName":"Goose Neck Bath Faucet","shortDescription":"A modern goose neck bath faucet that transforms your master ensuite into an open, modern bath space.","urlName":"Goose Neck Bath Faucet","price":{"usage":"Display","value":16.0,"description":"L","currency":"USD","minimumValue":16.0,"maximumValue":16.0},"parentCategories":["Fixtures"]}]}